sometools/__init__.py
sometools/https/__init__.py
sometools/https/downloader.py
sometools/images/__init__.py
sometools/images/photo.py
sometools/utils/__init__.py
sometools/utils/decorator.py
sometools/utils/files.py
sometools/utils/sessions.py
sometools/videos/__init__.py
sometools/videos/audio.py
sometools/videos/delogo.py
sometools/videos/split.py
setaire_sometools-1.0.20.dist-info/LICENSE
setaire_sometools-1.0.20.dist-info/METADATA
setaire_sometools-1.0.20.dist-info/WHEEL
setaire_sometools-1.0.20.dist-info/entry_points.txt
setaire_sometools-1.0.20.dist-info/top_level.txt
setaire_sometools-1.0.20.dist-info/RECORD
