Metadata-Version: 2.1
Name: setaire-sometools
Version: 1.0.20
Home-page: http://119.29.99.24:9980/setaire/sometools
Author: setaire
Author-email: 907391489@qq.com
License: MIT
Platform: any
Classifier: Development Status :: 4 - Beta
Classifier: License :: OSI Approved :: MIT License
Classifier: Operating System :: OS Independent
Classifier: Intended Audience :: Developers
Classifier: Programming Language :: Python :: 3 :: Only
Classifier: Programming Language :: Python :: 3.6
Classifier: Programming Language :: Python :: 3.7
Classifier: Programming Language :: Python :: 3.8
Classifier: Programming Language :: Python :: 3.9
Classifier: Programming Language :: Python :: 3.10
Classifier: Topic :: Software Development :: Libraries :: Python Modules
Requires-Python: >=3.6
License-File: LICENSE
Requires-Dist: moviepy ==1.0.3
Requires-Dist: aiohttp ==3.8.4
Requires-Dist: requests ==2.27.1
Requires-Dist: numpy ==1.25.2
Requires-Dist: opencv-python-headless ==4.8.0.76
